<?xml version="1.0" encoding="UTF-8"?>
<metadata xml:lang="en"><Esri><CreaDate>20181212</CreaDate><CreaTime>10500900</CreaTime><ArcGISFormat>1.0</ArcGISFormat><SyncOnce>TRUE</SyncOnce><DataProperties><lineage><Process ToolSource="c:\arcgis\desktop10.2\ArcToolbox\Toolboxes\Data Management Tools.tbx\CalculateField" Date="20150610" Time="115628">CalculateField hru_params_east_v2 DEM_ADJ [crt_land_e] VB #</Process><Process ToolSource="c:\arcgis\desktop10.2\ArcToolbox\Toolboxes\Data Management Tools.tbx\AddField" Date="20150630" Time="112520">AddField "D:\CarsonRiv\East Fork\HRU_PARAMS\hru_params_east_v2.shp" OUTFLOW DOUBLE # # # # NULLABLE NON_REQUIRED #</Process><Process ToolSource="c:\arcgis\desktop10.2\ArcToolbox\Toolboxes\Data Management Tools.tbx\CalculateField" Date="20150630" Time="122614">CalculateField hru_params_east_v2 DEM_ADJ [CRT_DEM] VB #</Process><Process ToolSource="c:\arcgis\desktop10.2\ArcToolbox\Toolboxes\Data Management Tools.tbx\CalculateField" Date="20150630" Time="125628">CalculateField hru_params_east_v2 DEM_ADJ [CRT_FILL] VB #</Process><Process ToolSource="c:\arcgis\desktop10.2\ArcToolbox\Toolboxes\Data Management Tools.tbx\CalculateField" Date="20150630" Time="130133">CalculateField hru_params_east_v2 DEM_ADJ [CRT_DEM] VB #</Process><Process ToolSource="c:\arcgis\desktop10.2\ArcToolbox\Toolboxes\Data Management Tools.tbx\CalculateField" Date="20150701" Time="103942">CalculateField hru_params_east_v2 MOIST_MAX 2.0 VB #</Process><Process ToolSource="c:\arcgis\desktop10.2\ArcToolbox\Toolboxes\Data Management Tools.tbx\CalculateField" Date="20150701" Time="104318">CalculateField hru_params_east_v2 RECHR_MAX 1.0 VB #</Process><Process ToolSource="c:\arcgis\desktop10.2\ArcToolbox\Toolboxes\Data Management Tools.tbx\CalculateField" Date="20150701" Time="111405">CalculateField hru_params_east_v2 MOIST_MAX 2 VB #</Process><Process ToolSource="c:\arcgis\desktop10.2\ArcToolbox\Toolboxes\Data Management Tools.tbx\CalculateField" Date="20150701" Time="113102">CalculateField hru_params_east_v2 RECHR_MAX 1 VB #</Process><Process ToolSource="c:\arcgis\desktop10.2\ArcToolbox\Toolboxes\Data Management Tools.tbx\CalculateField" Date="20150701" Time="114948">CalculateField hru_params_east_v2 MOIST_MAX .4 VB #</Process><Process ToolSource="c:\arcgis\desktop10.2\ArcToolbox\Toolboxes\Data Management Tools.tbx\CalculateField" Date="20150701" Time="115546">CalculateField hru_params_east_v2 RECHR_MAX .2 VB #</Process><Process ToolSource="c:\arcgis\desktop10.2\ArcToolbox\Toolboxes\Data Management Tools.tbx\CalculateField" Date="20150701" Time="124832">CalculateField hru_params_east_v2 MOIST_MAX .06 VB #</Process><Process ToolSource="c:\arcgis\desktop10.2\ArcToolbox\Toolboxes\Data Management Tools.tbx\CalculateField" Date="20150701" Time="125507">CalculateField hru_params_east_v2 RECHR_MAX .04 VB #</Process><Process ToolSource="c:\arcgis\desktop10.2\ArcToolbox\Toolboxes\Data Management Tools.tbx\CalculateField" Date="20150701" Time="142841">CalculateField hru_params_east_v2 MOIST_MAX 1 VB #</Process><Process ToolSource="c:\arcgis\desktop10.2\ArcToolbox\Toolboxes\Data Management Tools.tbx\CalculateField" Date="20150701" Time="142855">CalculateField hru_params_east_v2 RECHR_MAX .5 VB #</Process><Process ToolSource="c:\arcgis\desktop10.2\ArcToolbox\Toolboxes\Data Management Tools.tbx\CalculateField" Date="20150701" Time="143052">CalculateField hru_params_east_v2 MOIST_MAX .8 VB #</Process><Process ToolSource="c:\arcgis\desktop10.2\ArcToolbox\Toolboxes\Data Management Tools.tbx\CalculateField" Date="20150701" Time="143103">CalculateField hru_params_east_v2 RECHR_MAX .4 VB #</Process><Process ToolSource="c:\arcgis\desktop10.2\ArcToolbox\Toolboxes\Data Management Tools.tbx\AddField" Date="20150820" Time="105327">AddField "D:\CarsonRiv\East Fork\HRU_PARAMS\hru_params_east_v2.shp" OUTFLOWHRU DOUBLE # # # # NULLABLE NON_REQUIRED #</Process><Process ToolSource="c:\arcgis\desktop10.2\ArcToolbox\Toolboxes\Data Management Tools.tbx\CalculateField" Date="20150826" Time="162845">CalculateField "D:\CarsonRiv\East Fork\HRU_PARAMS\hru_params_east_v2.shp" ORIG_FID !FID! PYTHON #</Process><Process ToolSource="c:\arcgis\desktop10.2\ArcToolbox\Toolboxes\Data Management Tools.tbx\CalculateField" Date="20150826" Time="162942">CalculateField "D:\CarsonRiv\East Fork\HRU_PARAMS\hru_params_east_v2.shp" HRU_AREA !SHAPE.AREA@acres! PYTHON #</Process><Process ToolSource="c:\arcgis\desktop10.2\ArcToolbox\Toolboxes\Data Management Tools.tbx\CalculateField" Date="20150826" Time="162956">CalculateField "D:\CarsonRiv\East Fork\HRU_PARAMS\hru_params_east_v2.shp" HRUTYPE_IN 0 PYTHON #</Process><Process ToolSource="c:\arcgis\desktop10.2\ArcToolbox\Toolboxes\Data Management Tools.tbx\CalculateField" Date="20150826" Time="163010">CalculateField "D:\CarsonRiv\East Fork\HRU_PARAMS\hru_params_east_v2.shp" HRU_Type 0 PYTHON #</Process><Process ToolSource="c:\arcgis\desktop10.2\ArcToolbox\Toolboxes\Data Management Tools.tbx\CalculateField" Date="20150826" Time="163038">CalculateField "D:\CarsonRiv\East Fork\HRU_PARAMS\hru_params_east_v2.shp" HRU_Type !HRUTYPE_IN! PYTHON #</Process><Process ToolSource="c:\arcgis\desktop10.2\ArcToolbox\Toolboxes\Data Management Tools.tbx\CalculateField" Date="20150826" Time="164649">CalculateField "D:\CarsonRiv\East Fork\HRU_PARAMS\hru_params_east_v2.shp" ORIG_FID !FID! PYTHON #</Process><Process ToolSource="c:\arcgis\desktop10.2\ArcToolbox\Toolboxes\Data Management Tools.tbx\CalculateField" Date="20150826" Time="164745">CalculateField "D:\CarsonRiv\East Fork\HRU_PARAMS\hru_params_east_v2.shp" HRU_AREA !SHAPE.AREA@acres! PYTHON #</Process><Process ToolSource="c:\arcgis\desktop10.2\ArcToolbox\Toolboxes\Data Management Tools.tbx\CalculateField" Date="20150826" Time="164800">CalculateField "D:\CarsonRiv\East Fork\HRU_PARAMS\hru_params_east_v2.shp" HRUTYPE_IN 0 PYTHON #</Process><Process ToolSource="c:\arcgis\desktop10.2\ArcToolbox\Toolboxes\Data Management Tools.tbx\CalculateField" Date="20150826" Time="164814">CalculateField "D:\CarsonRiv\East Fork\HRU_PARAMS\hru_params_east_v2.shp" HRU_Type 0 PYTHON #</Process><Process ToolSource="c:\arcgis\desktop10.2\ArcToolbox\Toolboxes\Data Management Tools.tbx\CalculateField" Date="20150826" Time="164828">CalculateField "D:\CarsonRiv\East Fork\HRU_PARAMS\hru_params_east_v2.shp" LAKE_ID 0 PYTHON #</Process><Process ToolSource="c:\arcgis\desktop10.2\ArcToolbox\Toolboxes\Data Management Tools.tbx\CalculateField" Date="20150826" Time="164843">CalculateField "D:\CarsonRiv\East Fork\HRU_PARAMS\hru_params_east_v2.shp" LAKE_AREA 0 PYTHON #</Process><Process ToolSource="c:\arcgis\desktop10.2\ArcToolbox\Toolboxes\Data Management Tools.tbx\CalculateField" Date="20150826" Time="164918">CalculateField "D:\CarsonRiv\East Fork\HRU_PARAMS\hru_params_east_v2.shp" HRU_Type !HRUTYPE_IN! PYTHON #</Process><Process ToolSource="c:\arcgis\desktop10.2\ArcToolbox\Toolboxes\Data Management Tools.tbx\CalculateField" Date="20150827" Time="121720">CalculateField "D:\CarsonRiv\East Fork\HRU_PARAMS\hru_params_east_v2.shp" ORIG_FID !FID! PYTHON #</Process><Process ToolSource="c:\arcgis\desktop10.2\ArcToolbox\Toolboxes\Data Management Tools.tbx\CalculateField" Date="20150827" Time="121814">CalculateField "D:\CarsonRiv\East Fork\HRU_PARAMS\hru_params_east_v2.shp" HRU_AREA !SHAPE.AREA@acres! PYTHON #</Process><Process ToolSource="c:\arcgis\desktop10.2\ArcToolbox\Toolboxes\Data Management Tools.tbx\CalculateField" Date="20150827" Time="121828">CalculateField "D:\CarsonRiv\East Fork\HRU_PARAMS\hru_params_east_v2.shp" HRUTYPE_IN 0 PYTHON #</Process><Process ToolSource="c:\arcgis\desktop10.2\ArcToolbox\Toolboxes\Data Management Tools.tbx\CalculateField" Date="20150827" Time="121842">CalculateField "D:\CarsonRiv\East Fork\HRU_PARAMS\hru_params_east_v2.shp" HRU_Type 0 PYTHON #</Process><Process ToolSource="c:\arcgis\desktop10.2\ArcToolbox\Toolboxes\Data Management Tools.tbx\CalculateField" Date="20150827" Time="121909">CalculateField "D:\CarsonRiv\East Fork\HRU_PARAMS\hru_params_east_v2.shp" HRU_Type !HRUTYPE_IN! PYTHON #</Process><Process ToolSource="c:\arcgis\desktop10.2\ArcToolbox\Toolboxes\Data Management Tools.tbx\CalculateField" Date="20150831" Time="131605">CalculateField "D:\CarsonRiv\East Fork\HRU_PARAMS\hru_params_east_v2.shp" ORIG_FID !FID! PYTHON #</Process><Process ToolSource="c:\arcgis\desktop10.2\ArcToolbox\Toolboxes\Data Management Tools.tbx\CalculateField" Date="20150831" Time="131659">CalculateField "D:\CarsonRiv\East Fork\HRU_PARAMS\hru_params_east_v2.shp" HRU_AREA !SHAPE.AREA@acres! PYTHON #</Process><Process ToolSource="c:\arcgis\desktop10.2\ArcToolbox\Toolboxes\Data Management Tools.tbx\CalculateField" Date="20150831" Time="131714">CalculateField "D:\CarsonRiv\East Fork\HRU_PARAMS\hru_params_east_v2.shp" HRUTYPE_IN 0 PYTHON #</Process><Process ToolSource="c:\arcgis\desktop10.2\ArcToolbox\Toolboxes\Data Management Tools.tbx\CalculateField" Date="20150831" Time="131728">CalculateField "D:\CarsonRiv\East Fork\HRU_PARAMS\hru_params_east_v2.shp" HRU_Type 0 PYTHON #</Process><Process ToolSource="c:\arcgis\desktop10.2\ArcToolbox\Toolboxes\Data Management Tools.tbx\CalculateField" Date="20150831" Time="131742">CalculateField "D:\CarsonRiv\East Fork\HRU_PARAMS\hru_params_east_v2.shp" LAKE_ID 0 PYTHON #</Process><Process ToolSource="c:\arcgis\desktop10.2\ArcToolbox\Toolboxes\Data Management Tools.tbx\CalculateField" Date="20150831" Time="131756">CalculateField "D:\CarsonRiv\East Fork\HRU_PARAMS\hru_params_east_v2.shp" LAKE_AREA 0 PYTHON #</Process><Process ToolSource="c:\arcgis\desktop10.2\ArcToolbox\Toolboxes\Data Management Tools.tbx\CalculateField" Date="20150831" Time="131825">CalculateField "D:\CarsonRiv\East Fork\HRU_PARAMS\hru_params_east_v2.shp" HRU_Type !HRUTYPE_IN! PYTHON #</Process><Process ToolSource="c:\arcgis\desktop10.2\ArcToolbox\Toolboxes\Data Management Tools.tbx\CalculateField" Date="20150831" Time="163538">CalculateField hru_params_east_v2 DEM_ADJ_Lk [DEM_ADJ] VB #</Process><Process ToolSource="c:\arcgis\desktop10.2\ArcToolbox\Toolboxes\Data Management Tools.tbx\CalculateField" Date="20150831" Time="164412">CalculateField hru_params_east_v2 DEM_ADJ [CRT_DEM] VB #</Process><Process ToolSource="c:\arcgis\desktop10.3\ArcToolbox\Toolboxes\Data Management Tools.tbx\CalculateField" Date="20150917" Time="112812">CalculateField "D:\CarsonRiv\East Fork\HRU_PARAMS\hru_params_east_v2.shp" ORIG_FID !FID! PYTHON #</Process><Process ToolSource="c:\arcgis\desktop10.3\ArcToolbox\Toolboxes\Data Management Tools.tbx\CalculateField" Date="20150917" Time="112859">CalculateField "D:\CarsonRiv\East Fork\HRU_PARAMS\hru_params_east_v2.shp" HRU_AREA !SHAPE.AREA@acres! PYTHON #</Process><Process ToolSource="c:\arcgis\desktop10.3\ArcToolbox\Toolboxes\Data Management Tools.tbx\CalculateField" Date="20150917" Time="112900">CalculateField "D:\CarsonRiv\East Fork\HRU_PARAMS\hru_params_east_v2.shp" HRUTYPE_IN 0 PYTHON #</Process><Process ToolSource="c:\arcgis\desktop10.3\ArcToolbox\Toolboxes\Data Management Tools.tbx\CalculateField" Date="20150917" Time="112901">CalculateField "D:\CarsonRiv\East Fork\HRU_PARAMS\hru_params_east_v2.shp" HRU_Type 0 PYTHON #</Process><Process ToolSource="c:\arcgis\desktop10.3\ArcToolbox\Toolboxes\Data Management Tools.tbx\CalculateField" Date="20150917" Time="112902">CalculateField "D:\CarsonRiv\East Fork\HRU_PARAMS\hru_params_east_v2.shp" LAKE_ID 0 PYTHON #</Process><Process ToolSource="c:\arcgis\desktop10.3\ArcToolbox\Toolboxes\Data Management Tools.tbx\CalculateField" Date="20150917" Time="112903">CalculateField "D:\CarsonRiv\East Fork\HRU_PARAMS\hru_params_east_v2.shp" LAKE_AREA 0 PYTHON #</Process><Process ToolSource="c:\arcgis\desktop10.3\ArcToolbox\Toolboxes\Data Management Tools.tbx\CalculateField" Date="20150917" Time="112925">CalculateField "D:\CarsonRiv\East Fork\HRU_PARAMS\hru_params_east_v2.shp" HRU_Type !HRUTYPE_IN! PYTHON #</Process><Process ToolSource="c:\arcgis\desktop10.3\ArcToolbox\Toolboxes\Data Management Tools.tbx\CalculateField" Date="20160720" Time="104627">CalculateField D:\CarsonRiv\East_Fork\HRU_PARAMS\hru_params_east_v2.shp PPT_ZONE 0 PYTHON #</Process><Process ToolSource="c:\arcgis\desktop10.3\ArcToolbox\Toolboxes\Data Management Tools.tbx\CalculateField" Date="20160720" Time="104830">CalculateField D:\CarsonRiv\East_Fork\HRU_PARAMS\hru_params_east_v2.shp PPT_ZONE 0 PYTHON #</Process><Process ToolSource="c:\arcgis\desktop10.3\ArcToolbox\Toolboxes\Data Management Tools.tbx\CalculateField" Date="20160720" Time="110047">CalculateField D:\CarsonRiv\East_Fork\HRU_PARAMS\hru_params_east_v2.shp PPT_ZONE 0 PYTHON #</Process><Process ToolSource="c:\arcgis\desktop10.3\ArcToolbox\Toolboxes\Data Management Tools.tbx\CalculateField" Date="20160720" Time="144631">CalculateField D:\CarsonRiv\East_Fork\HRU_PARAMS\hru_params_east_v2.shp PPT_ZONE 0 PYTHON #</Process><Process ToolSource="c:\arcgis\desktop10.3\ArcToolbox\Toolboxes\Data Management Tools.tbx\CalculateField" Date="20160907" Time="113512">CalculateField D:\CarsonRiv\East_Fork\HRU_PARAMS\hru_params_east_v2.shp PPT_ZONE 0 PYTHON #</Process><Process ToolSource="c:\arcgis\desktop10.3\ArcToolbox\Toolboxes\Data Management Tools.tbx\CalculateField" Date="20160907" Time="120637">CalculateField D:\CarsonRiv\East_Fork\HRU_PARAMS\hru_params_east_v2.shp PPT_ZONE 0 PYTHON #</Process><Process ToolSource="c:\arcgis\desktop10.3\ArcToolbox\Toolboxes\Data Management Tools.tbx\CalculateField" Date="20160916" Time="140338">CalculateField hru_polygon_layer COV_TYPE 0 PYTHON #</Process><Process ToolSource="c:\arcgis\desktop10.3\ArcToolbox\Toolboxes\Data Management Tools.tbx\CalculateField" Date="20160916" Time="140338">CalculateField hru_polygon_layer COVDEN_SUM 0 PYTHON #</Process><Process ToolSource="c:\arcgis\desktop10.3\ArcToolbox\Toolboxes\Data Management Tools.tbx\CalculateField" Date="20160916" Time="140338">CalculateField hru_polygon_layer COVDEN_WIN 0 PYTHON #</Process><Process ToolSource="c:\arcgis\desktop10.3\ArcToolbox\Toolboxes\Data Management Tools.tbx\CalculateField" Date="20160916" Time="140339">CalculateField hru_polygon_layer SNOW_INTCP 0 PYTHON #</Process><Process ToolSource="c:\arcgis\desktop10.3\ArcToolbox\Toolboxes\Data Management Tools.tbx\CalculateField" Date="20160916" Time="140339">CalculateField hru_polygon_layer SRAIN_INTC 0 PYTHON #</Process><Process ToolSource="c:\arcgis\desktop10.3\ArcToolbox\Toolboxes\Data Management Tools.tbx\CalculateField" Date="20160916" Time="140339">CalculateField hru_polygon_layer WRAIN_INTC 0 PYTHON #</Process><Process ToolSource="c:\arcgis\desktop10.3\ArcToolbox\Toolboxes\Data Management Tools.tbx\CalculateField" Date="20160916" Time="140339">CalculateField hru_polygon_layer RAD_TRNCF 0 PYTHON #</Process><Process ToolSource="c:\arcgis\desktop10.3\ArcToolbox\Toolboxes\Data Management Tools.tbx\CalculateField" Date="20160919" Time="144835">CalculateField D:\CarsonRiv\East_Fork\HRU_PARAMS\hru_params_east_v2.shp PPT_ZONE 0 PYTHON #</Process><Process ToolSource="c:\arcgis\desktop10.3\ArcToolbox\Toolboxes\Data Management Tools.tbx\CalculateField" Date="20161102" Time="115410">CalculateField hru_polygon_layer SOIL_TYPE soil_type_func(!CLAY_PCT!, !SAND_PCT!) PYTHON "def soil_type_func(clay, sand):\n    if sand &gt; 50: return 1\n    elif clay &gt; 40: return 3\n    else: return 2\n"</Process><Process ToolSource="c:\arcgis\desktop10.3\ArcToolbox\Toolboxes\Data Management Tools.tbx\CalculateField" Date="20161102" Time="115411">CalculateField hru_polygon_layer SOIL_TYPE 0 PYTHON #</Process><Process ToolSource="c:\arcgis\desktop10.3\ArcToolbox\Toolboxes\Data Management Tools.tbx\CalculateField" Date="20161102" Time="115415">CalculateField D:\CarsonRiv\East_Fork\HRU_PARAMS\hru_params_east_v2.shp MOIST_INIT "!MOIST_MAX! * 0.1" PYTHON #</Process><Process ToolSource="c:\arcgis\desktop10.3\ArcToolbox\Toolboxes\Data Management Tools.tbx\CalculateField" Date="20161102" Time="115416">CalculateField hru_polygon_layer MOIST_INIT 0 PYTHON #</Process><Process ToolSource="c:\arcgis\desktop10.3\ArcToolbox\Toolboxes\Data Management Tools.tbx\CalculateField" Date="20161102" Time="115417">CalculateField hru_polygon_layer MOIST_MAX 0 PYTHON #</Process><Process ToolSource="c:\arcgis\desktop10.3\ArcToolbox\Toolboxes\Data Management Tools.tbx\CalculateField" Date="20161102" Time="115421">CalculateField D:\CarsonRiv\East_Fork\HRU_PARAMS\hru_params_east_v2.shp RECHR_INIT "!RECHR_MAX! * 0.1" PYTHON #</Process><Process ToolSource="c:\arcgis\desktop10.3\ArcToolbox\Toolboxes\Data Management Tools.tbx\CalculateField" Date="20161102" Time="115422">CalculateField hru_polygon_layer RECHR_INIT 0 PYTHON #</Process><Process ToolSource="c:\arcgis\desktop10.3\ArcToolbox\Toolboxes\Data Management Tools.tbx\CalculateField" Date="20161102" Time="115423">CalculateField hru_polygon_layer RECHR_MAX 0 PYTHON #</Process><Process ToolSource="c:\arcgis\desktop10.3\ArcToolbox\Toolboxes\Data Management Tools.tbx\CalculateField" Date="20161102" Time="115425">CalculateField hru_polygon_layer SSR2G_RATE "(!KSAT! * (3600 * 24 / (2.54 * 10000))) / (!MOIST_MAX! * (!SAND_PCT!/ 100))" PYTHON #</Process><Process ToolSource="c:\arcgis\desktop10.3\ArcToolbox\Toolboxes\Data Management Tools.tbx\CalculateField" Date="20161102" Time="115426">CalculateField hru_polygon_layer SSR2G_RATE 0 PYTHON #</Process><Process ToolSource="c:\arcgis\desktop10.3\ArcToolbox\Toolboxes\Data Management Tools.tbx\CalculateField" Date="20161102" Time="115429">CalculateField hru_polygon_layer SLOWCOEF_L slowcoef_lin(!KSAT!, !HRU_SLP_R!, 550.0) PYTHON "def slowcoef_lin(ksat, slope, cs):\n    return 0.1 * ksat * 0.0864 * math.sin(slope) / cs\n"</Process><Process ToolSource="c:\arcgis\desktop10.3\ArcToolbox\Toolboxes\Data Management Tools.tbx\CalculateField" Date="20161102" Time="115430">CalculateField hru_polygon_layer SLOWCOEF_L 0 PYTHON #</Process><Process ToolSource="c:\arcgis\desktop10.3\ArcToolbox\Toolboxes\Data Management Tools.tbx\CalculateField" Date="20161102" Time="115432">CalculateField hru_polygon_layer SLOWCOEF_S slowcoef_sq(!KSAT!, !HRU_SLP_R!, !MOIST_MAX!, !SAND_PCT!, 550.0) PYTHON "def slowcoef_sq(ksat, slope, moist_max, sand, cs):\n    return 0.9 * (ksat * 0.0864 * math.sin(slope) / (moist_max * (sand / 100) * cs))\n"</Process><Process ToolSource="c:\arcgis\desktop10.3\ArcToolbox\Toolboxes\Data Management Tools.tbx\CalculateField" Date="20161102" Time="115433">CalculateField hru_polygon_layer SLOWCOEF_S 0 PYTHON #</Process><Process ToolSource="c:\arcgis\desktop10.5\ArcToolbox\Toolboxes\Data Management Tools.tbx\DeleteField" Date="20181212" Time="105906">DeleteField east_fk_active LatDDNAD83;LongDDNAD8;Elevation_;ElevationS;SHAPE_Leng;SHAPE_Area;ORIG_FID;HRU_ID;HRUTYPE_IN;DEM_MEAN;DEM_MEDIAN;DEM_MIN;DEM_MAX;DEM_FLOWAC;DEM_SUM;DEM_COUNT;DEM_SINK8;DEM_SINK4;CRT_DEM;CRT_FILL;HRU_ELEV;HRU_AREA;HRU_ASPECT;HRU_SLP_D;HRU_SLP_R;HRU_SLP_P;HRU_ROW;HRU_COL;HRU_X;HRU_Y;HRU_LAT;HRU_LON;LAKE_ID;LAKE_AREA;ISEG;IRUNBOUND;FLOW_DIR;KRCH;IRCH;JRCH;IREACH;RCHLEN;MAXREACH;OUTSEG;IUPSEG;SUB_BASIN;SEG_BASIN;STRM_TOP;STRM_SLOPE;PPT_ZONE;JH_TMAX;JH_TMIN;JH_COEF;SNAREA_THR;TMAX_ADJ;TMIN_ADJ;COV_TYPE;COVDEN_SUM;COVDEN_WIN;RAD_TRNCF;SNOW_INTCP;SRAIN_INTC;WRAIN_INTC;AWC;CLAY_PCT;SAND_PCT;KSAT;SOIL_DEPTH;ROOT_DEPTH;SOIL_TYPE;MOIST_INIT;MOIST_MAX;RECHR_INIT;RECHR_MAX;SSR2G_RATE;SLOWCOEF_L;SLOWCOEF_S;FASTCOEF_L;FASTCOEF_S;IMPERV_PCT;CAREA_MAX;PPT_01;PPT_02;PPT_03;PPT_04;PPT_05;PPT_06;PPT_07;PPT_08;PPT_09;PPT_10;PPT_11;PPT_12;PPT_14;TMAX_01;TMAX_02;TMAX_03;TMAX_04;TMAX_05;TMAX_06;TMAX_07;TMAX_08;TMAX_09;TMAX_10;TMAX_11;TMAX_12;TMAX_14;TMIN_01;TMIN_02;TMIN_03;TMIN_04;TMIN_05;TMIN_06;TMIN_07;TMIN_08;TMIN_09;TMIN_10;TMIN_11;TMIN_12;TMIN_14;PPT_RT_01;PPT_RT_02;PPT_RT_03;PPT_RT_04;PPT_RT_05;PPT_RT_06;PPT_RT_07;PPT_RT_08;PPT_RT_09;PPT_RT_10;PPT_RT_11;PPT_RT_12;crt_land_e;DEM_ADJ;OUTFLOW;OUTFLOWHRU;DEM_ADJ_Lk;UTM_x;UTM_y</Process><Process ToolSource="c:\arcgis\desktop10.5\ArcToolbox\Toolboxes\Data Management Tools.tbx\CalculateField" Date="20181212" Time="110330">CalculateField east_fk_active Active "IF [HRU_Type] &gt; 1, 1, 0" VB #</Process><Process ToolSource="c:\arcgis\desktop10.5\ArcToolbox\Toolboxes\Data Management Tools.tbx\CalculateField" Date="20181212" Time="110629">CalculateField east_fk_active Active 1 VB #</Process><Process ToolSource="c:\arcgis\desktop10.5\ArcToolbox\Toolboxes\Data Management Tools.tbx\CalculateField" Date="20181212" Time="110725">CalculateField east_fk_active Active 0 VB #</Process></lineage></DataProperties></Esri></metadata>
